[
  {
    "id": "4224f1e8-1163-4e58-83b7-345fc6b16678",
    "label": "2",
    "hour": 14,
    "minute": 9,
    "enabled": false,
    "repeat": 0,
    "sound": "",
    "snooze_min": 5,
    "fullscreen": true
  },
  {
    "id": "b8a1a31d-9c03-44a8-bc89-8f28aeabd14d",
    "label": "闹钟",
    "hour": 14,
    "minute": 10,
    "enabled": false,
    "repeat": 0,
    "sound": "",
    "snooze_min": 5,
    "fullscreen": true
  },
  {
    "id": "920a55f6-d6f8-46af-9932-73591e0c8221",
    "label": "闹钟",
    "hour": 14,
    "minute": 22,
    "enabled": false,
    "repeat": 0,
    "sound": "",
    "snooze_min": 5,
    "fullscreen": true
  },
  {
    "id": "ca11eca5-af6b-49ba-8410-3140f0c292c8",
    "label": "闹钟",
    "hour": 14,
    "minute": 34,
    "enabled": false,
    "repeat": 0,
    "sound": "",
    "snooze_min": 5,
    "fullscreen": true
  }
]