{
  "stats": {
    "world_time": {
      "visit_count": 220,
      "last_visit": 1773674193.8624706,
      "total_session_ms": 0,
      "session_count": 0,
      "tod_slots": [
        8,
        0,
        1,
        22,
        24,
        20,
        18,
        127
      ]
    },
    "alarm": {
      "visit_count": 104,
      "last_visit": 1773673180.0764098,
      "total_session_ms": 0,
      "session_count": 0,
      "tod_slots": [
        0,
        0,
        0,
        15,
        16,
        13,
        13,
        47
      ]
    },
    "timer": {
      "visit_count": 124,
      "last_visit": 1773671382.045318,
      "total_session_ms": 0,
      "session_count": 25,
      "tod_slots": [
        3,
        0,
        0,
        18,
        15,
        13,
        8,
        67
      ]
    },
    "stopwatch": {
      "visit_count": 82,
      "last_visit": 1773673180.5720758,
      "total_session_ms": 0,
      "session_count": 0,
      "tod_slots": [
        0,
        0,
        0,
        15,
        9,
        12,
        4,
        42
      ]
    },
    "focus": {
      "visit_count": 85,
      "last_visit": 1773671348.4080267,
      "total_session_ms": 0,
      "session_count": 6,
      "tod_slots": [
        0,
        0,
        0,
        13,
        9,
        14,
        6,
        43
      ]
    },
    "plugin": {
      "visit_count": 210,
      "last_visit": 1773673926.445416,
      "total_session_ms": 0,
      "session_count": 0,
      "tod_slots": [
        5,
        0,
        2,
        26,
        31,
        45,
        19,
        82
      ]
    },
    "automation": {
      "visit_count": 151,
      "last_visit": 1773671526.5650542,
      "total_session_ms": 0,
      "session_count": 0,
      "tod_slots": [
        2,
        0,
        2,
        20,
        15,
        29,
        18,
        65
      ]
    }
  },
  "feature_labels": {
    "world_time": "世界时间",
    "alarm": "闹钟",
    "timer": "计时器",
    "stopwatch": "秒表",
    "focus": "专注模式",
    "plugin": "插件",
    "automation": "自动化"
  }
}